MANIFEST.in
README.md
setup.cfg
setup.py
django_reviewing.egg-info/PKG-INFO
django_reviewing.egg-info/SOURCES.txt
django_reviewing.egg-info/dependency_links.txt
django_reviewing.egg-info/requires.txt
django_reviewing.egg-info/top_level.txt
reviews/__init__.py
reviews/admin.py
reviews/admin_filter.py
reviews/managers.py
reviews/models.py
reviews/settings.py
reviews/migrations/0001_initial.py
reviews/migrations/0002_auto_20170912_1154.py
reviews/migrations/0003_auto_20170912_1622.py
reviews/migrations/0004_auto_20170914_1417.py
reviews/migrations/0005_auto_20170915_1148.py
reviews/migrations/0006_review_title.py
reviews/migrations/0007_review_display_date.py
reviews/migrations/0008_review_highlight.py
reviews/migrations/0009_auto_20180611_1145.py
reviews/migrations/0010_auto_20180611_1420.py
reviews/migrations/0011_auto_20180611_1422.py
reviews/migrations/0012_remove_review_highlight.py
reviews/migrations/__init__.py